bot/__init__.py
bot/bot.py
client/__init__.py
client/api.py
logger/__init__.py
logger/loggers.py
samples/__init__.py
samples/sample.py
samples/sample_2.py
samples/sample_2_yaml.py
samples/sample_db.py
samples/sample_db_2.py
server/__init__.py
server/server.py
server/web.py
slackbot_workout/__init__.py
slackbot_workout/api.py
slackbot_workout/bot.py
slackbot_workout/configurators.py
slackbot_workout/loggers.py
slackbot_workout/manager.py
slackbot_workout/server.py
slackbot_workout/user.py
slackbot_workout/web.py
slackbot_workout-0.3.dist-info/DESCRIPTION.rst
slackbot_workout-0.3.dist-info/METADATA
slackbot_workout-0.3.dist-info/RECORD
slackbot_workout-0.3.dist-info/WHEEL
slackbot_workout-0.3.dist-info/metadata.json
slackbot_workout-0.3.dist-info/top_level.txt
test/__init__.py
test/integration_tests/__init__.py
test/integration_tests/test_csv_logger.py
test/integration_tests/test_postgres_database_logger.py
test/unit_tests/__init__.py
test/unit_tests/test_bot.py
test/unit_tests/test_user.py
test/unit_tests/test_user_manager.py
test/unit_tests/test_web.py
user/__init__.py
user/manager.py
user/user.py
util/__init__.py
util/configurators.py
util/fetchChannelId.py
