Metadata-Version: 2.0
Name: slackbot-workout
Version: 0.3
Summary: A fun framework for incorporating more exercise into your life at work through Slack.
Home-page: UNKNOWN
Author: Brandon Shin, Miles Yucht
Author-email: mgyucht@gmail.com
License: MIT
Keywords: slack slackbot exercise
Platform: UNKNOWN
Requires-Dist: cherrypy (>=4.0.0)
Requires-Dist: psycopg2 (>=2.6.1)
Requires-Dist: pyyaml (>=3.11)
Requires-Dist: slacker (>=0.8.6)
